HISTORY.rst
LICENSE
MANIFEST.in
NOTICE
README.rst
requirements.txt
setup.cfg
setup.py
test_requests.py
requests/__init__.py
requests/adapters.py
requests/api.py
requests/auth.py
requests/cacert.pem
requests/certs.py
requests/compat.py
requests/cookies.py
requests/exceptions.py
requests/hooks.py
requests/models.py
requests/sessions.py
requests/status_codes.py
requests/structures.py
requests/utils.py
requests/packages/__init__.py
requests/packages/charade/__init__.py
requests/packages/charade/__main__.py
requests/packages/charade/big5freq.py
requests/packages/charade/big5prober.py
requests/packages/charade/chardistribution.py
requests/packages/charade/charsetgroupprober.py
requests/packages/charade/charsetprober.py
requests/packages/charade/codingstatemachine.py
requests/packages/charade/compat.py
requests/packages/charade/constants.py
requests/packages/charade/cp949prober.py
requests/packages/charade/escprober.py
requests/packages/charade/escsm.py
requests/packages/charade/eucjpprober.py
requests/packages/charade/euckrfreq.py
requests/packages/charade/euckrprober.py
requests/packages/charade/euctwfreq.py
requests/packages/charade/euctwprober.py
requests/packages/charade/gb2312freq.py
requests/packages/charade/gb2312prober.py
requests/packages/charade/hebrewprober.py
requests/packages/charade/jisfreq.py
requests/packages/charade/jpcntx.py
requests/packages/charade/langbulgarianmodel.py
requests/packages/charade/langcyrillicmodel.py
requests/packages/charade/langgreekmodel.py
requests/packages/charade/langhebrewmodel.py
requests/packages/charade/langhungarianmodel.py
requests/packages/charade/langthaimodel.py
requests/packages/charade/latin1prober.py
requests/packages/charade/mbcharsetprober.py
requests/packages/charade/mbcsgroupprober.py
requests/packages/charade/mbcssm.py
requests/packages/charade/sbcharsetprober.py
requests/packages/charade/sbcsgroupprober.py
requests/packages/charade/sjisprober.py
requests/packages/charade/universaldetector.py
requests_SSL_v3.egg-info/PKG-INFO
requests_SSL_v3.egg-info/SOURCES.txt
requests_SSL_v3.egg-info/dependency_links.txt
requests_SSL_v3.egg-info/not-zip-safe
requests_SSL_v3.egg-info/top_level.txt