Metadata-Version: 1.1
Name: requests-SSL-v3
Version: 2.1.0
Summary: Python HTTP for Humans.
Home-page: http://python-requests.org, https://github.com/anantasty/requests
Author: Kenneth Reitz, Anant Asthana
Author-email: anant.asty@gmail.com, me@kennethreitz.com
License: Copyright 2013 Kenneth Reitz
